myrs/__init__.py
myrs/myrs.py
myrs-0.0.2.dist-info/METADATA
myrs-0.0.2.dist-info/WHEEL
myrs-0.0.2.dist-info/RECORD
