Metadata-Version: 2.1
Name: myrs
Version: 0.0.2
Summary: The friendly scientific machine learning library
License: new BSD
Author: altar31
Author-email: damien.sicard31@gmail.com
Requires-Python: >=3.11,<4.0
Classifier: License :: Other/Proprietary License
Classifier: Programming Language :: Python :: 3
Classifier: Programming Language :: Python :: 3.11
Requires-Dist: keras (>=2.13.1,<3.0.0)
Requires-Dist: pandas (>=2.0.3,<3.0.0)
Requires-Dist: scikit-learn (>=1.3.0,<2.0.0)
Requires-Dist: seaborn (>=0.12.2,<0.13.0)
